README.txt
setup.py
darts/__init__.py
darts.util.events.egg-info/PKG-INFO
darts.util.events.egg-info/SOURCES.txt
darts.util.events.egg-info/dependency_links.txt
darts.util.events.egg-info/namespace_packages.txt
darts.util.events.egg-info/top_level.txt
darts.util.events.egg-info/zip-safe
darts/lib/__init__.py
darts/lib/utils/__init__.py
darts/lib/utils/event.py
doc/Makefile
doc/conf.py
doc/index.txt
example/attribute_events.py