Metadata-Version: 1.0
Name: darts.util.events
Version: 0.4
Summary: Simple C#-style event dispatcher
Home-page: UNKNOWN
Author: Deterministic Arts
Author-email: contact@deterministic-arts.de
License: MIT
Platform: UNKNOWN
